array_api_signal/__init__.py
array_api_signal/_version.py
array_api_signal/integral.py
array_api_signal/signal.py
array_api_signal/windows.py
array_api_signal/wrapper.py
array_api_signal-0.1.0.dist-info/licenses/LICENSE
array_api_signal-0.1.0.dist-info/METADATA
array_api_signal-0.1.0.dist-info/WHEEL
array_api_signal-0.1.0.dist-info/top_level.txt
array_api_signal-0.1.0.dist-info/RECORD
