Metadata-Version: 2.4
Name: array-api-signal
Version: 0.1.0
Summary: Signal Processing Extensions to the Python Array API
Author-email: James Kennington <jameswkennington@gmail.com>
License: MPL-2.0
Project-URL: Homepage, https://git.ligo.org/james.kennington/array-api-signal
Project-URL: Documentation, https://docs.ligo.org/james.kennington/array-api-signal
Project-URL: Issues, https://git.ligo.org/james.kennington/array-api-signal/issues
Classifier: Programming Language :: Python :: 3
Classifier: License :: OSI Approved :: Mozilla Public License 2.0 (MPL 2.0)
Classifier: Operating System :: OS Independent
Requires-Python: >=3.10
License-File: LICENSE
Requires-Dist: array-api-compat
Requires-Dist: array-api-extra
Provides-Extra: test
Requires-Dist: pytest; extra == "test"
Requires-Dist: pytest-cov; extra == "test"
Requires-Dist: numpy; extra == "test"
Requires-Dist: scipy; extra == "test"
Requires-Dist: torch; extra == "test"
Provides-Extra: lint
Requires-Dist: black; extra == "lint"
Requires-Dist: flake8; extra == "lint"
Requires-Dist: flake8-bandit; extra == "lint"
Requires-Dist: flake8-black; extra == "lint"
Requires-Dist: flake8-bugbear; extra == "lint"
Requires-Dist: flake8-future-annotations; extra == "lint"
Requires-Dist: flake8-isort; extra == "lint"
Requires-Dist: flake8-logging-format; extra == "lint"
Requires-Dist: flake8-pyproject; extra == "lint"
Requires-Dist: isort; extra == "lint"
Requires-Dist: mypy; extra == "lint"
Requires-Dist: mypy-extensions; extra == "lint"
Provides-Extra: dev
Requires-Dist: array_api_signal[lint]; extra == "dev"
Requires-Dist: array_api_signal[test]; extra == "dev"
Dynamic: license-file
